Metadata-Version: 2.1
Name: nr-crucible
Version: 1.0.0
Summary: Crucible tools
Home-page: https://github.com/johnnyrockets/crucible
Author: John Bisignano
Author-email: jbiz@pm.me
License: MIT license
Keywords: crucible
Platform: UNKNOWN
Classifier: Development Status :: 2 - Pre-Alpha
Classifier: Intended Audience :: Developers
Classifier: License :: OSI Approved :: MIT License
Classifier: Natural Language :: English
Classifier: Programming Language :: Python :: 3
Classifier: Programming Language :: Python :: 3.6
Classifier: Programming Language :: Python :: 3.7
Classifier: Programming Language :: Python :: 3.8
Requires-Python: >=3.6
License-File: LICENSE
License-File: AUTHORS.rst
